matplotcheck/__init__.py
matplotcheck/autograde.py
matplotcheck/base.py
matplotcheck/cases.py
matplotcheck/folium.py
matplotcheck/notebook.py
matplotcheck/py.typed
matplotcheck/raster.py
matplotcheck/timeseries.py
matplotcheck/vector.py
matplotcheck/tests/__init__.py
matplotcheck/tests/conftest.py
matplotcheck/tests/test_autograde.py
matplotcheck/tests/test_base.py
matplotcheck/tests/test_base_axis.py
matplotcheck/tests/test_base_data.py
matplotcheck/tests/test_base_legends.py
matplotcheck/tests/test_base_lines.py
matplotcheck/tests/test_base_titles_captions.py
matplotcheck/tests/test_lines.py
matplotcheck/tests/test_points.py
matplotcheck/tests/test_polygons.py
matplotcheck/tests/test_raster.py
matplotcheck/tests/test_timeseries_module.py
matplotcheck2-0.2.1.dist-info/licenses/LICENSE
matplotcheck2-0.2.1.dist-info/METADATA
matplotcheck2-0.2.1.dist-info/WHEEL
matplotcheck2-0.2.1.dist-info/top_level.txt
matplotcheck2-0.2.1.dist-info/RECORD
