Metadata-Version: 2.4
Name: matplotcheck2
Version: 0.2.1
Summary: Functions to check Matplotlib plot outputs
Author-email: Leah Wasser <leah.wasser@colorado.edu>
Maintainer-email: Pete Stenger <pete@stenger.io>, Eliot Robson <eliot.robson24@gmail.com>
Project-URL: documentation, https://matplotcheck2.readthedocs.io/en/latest/
Project-URL: homepage, https://github.com/matplotcheck/matplotcheck
Project-URL: source, https://github.com/matplotcheck/matplotcheck
Classifier: Intended Audience :: Developers
Classifier: License :: OSI Approved :: BSD License
Classifier: Programming Language :: Python
Classifier: Topic :: Software Development
Classifier: Operating System :: Microsoft :: Windows
Classifier: Operating System :: POSIX
Classifier: Operating System :: Unix
Classifier: Operating System :: MacOS
Requires-Python: >=3.10
License-File: LICENSE
Requires-Dist: matplotlib>=3.10.1
Requires-Dist: numpy>=2.0.0
Requires-Dist: pandas>=2.0.0
Provides-Extra: docs
Requires-Dist: furo>=2024.8.6; extra == "docs"
Requires-Dist: sphinx>=8.1.3; extra == "docs"
Requires-Dist: sphinx-autobuild>=2024.10.3; extra == "docs"
Requires-Dist: sphinx-gallery>=0.19.0; extra == "docs"
Provides-Extra: spatial
Requires-Dist: geopandas>=1.0.1; extra == "spatial"
Requires-Dist: shapely>=2.0.0; extra == "spatial"
Provides-Extra: timeseries
Requires-Dist: scipy>=1.15.2; extra == "timeseries"
Requires-Dist: python-dateutil>=2.8.0; extra == "timeseries"
Provides-Extra: folium
Requires-Dist: folium>=0.19.5; extra == "folium"
Provides-Extra: all
Requires-Dist: geopandas>=1.0.1; extra == "all"
Requires-Dist: shapely>=2.0.0; extra == "all"
Requires-Dist: scipy>=1.15.2; extra == "all"
Requires-Dist: python-dateutil>=2.8.0; extra == "all"
Requires-Dist: folium>=0.19.5; extra == "all"
Dynamic: license-file
